<annotation>
	<folder>image</folder>
	<filename>image10.jpg</filename>
	<path>/home/techcare/Downloads/image/image10.jpg</path>
	<source>
		<database>Unknown</database>
	</source>
	<size>
		<width>640</width>
		<height>491</height>
		<depth>3</depth>
	</size>
	<segmented>0</segmented>
	<object>
		<name>worker</name>
		<pose>Unspecified</pose>
		<truncated>0</truncated>
		<difficult>0</difficult>
		<bndbox>
			<xmin>286</xmin>
			<ymin>119</ymin>
			<xmax>389</xmax>
			<ymax>350</ymax>
		</bndbox>
	</object>
	<object>
		<name>worker</name>
		<pose>Unspecified</pose>
		<truncated>0</truncated>
		<difficult>0</difficult>
		<bndbox>
			<xmin>224</xmin>
			<ymin>172</ymin>
			<xmax>304</xmax>
			<ymax>376</ymax>
		</bndbox>
	</object>
</annotation>
